[
  {
    "src": "image10.jpg",
    "label": ""
  },
  {
    "src": "image15.jpg",
    "label": ""
  },
  {
    "src": "image21.jpg",
    "label": ""
  },
  {
    "src": "image22.jpg",
    "label": ""
  },
  {
    "src": "image28.jpg",
    "label": ""
  },
  {
    "src": "image29.jpg",
    "label": ""
  },
  {
    "src": "image32.jpg",
    "label": ""
  },
  {
    "src": "image34.jpg",
    "label": ""
  },
  {
    "src": "image37.jpg",
    "label": ""
  },
  {
    "src": "image44.jpg",
    "label": ""
  },
  {
    "src": "image48.jpg",
    "label": ""
  },
  {
    "src": "image55.jpg",
    "label": ""
  },
  {
    "src": "image58.jpg",
    "label": ""
  },
  {
    "src": "image75.jpg",
    "label": ""
  },
  {
    "src": "image89.jpg",
    "label": ""
  },
  {
    "src": "image92.jpg",
    "label": ""
  },
  {
    "src": "image103.jpg",
    "label": ""
  },
  {
    "src": "image110.jpg",
    "label": ""
  },
  {
    "src": "image111.jpg",
    "label": ""
  },
  {
    "src": "image114.jpg",
    "label": ""
  },
  {
    "src": "image116.jpg",
    "label": ""
  },
  {
    "src": "image130.jpg",
    "label": ""
  },
  {
    "src": "image143.jpg",
    "label": ""
  },
  {
    "src": "image197.jpg",
    "label": ""
  },
  {
    "src": "image204.jpg",
    "label": ""
  },
  {
    "src": "image218.jpg",
    "label": ""
  },
  {
    "src": "image234.jpg",
    "label": ""
  },
  {
    "src": "image249.jpg",
    "label": ""
  },
  {
    "src": "image260.jpg",
    "label": ""
  },
  {
    "src": "image269.jpg",
    "label": ""
  },
  {
    "src": "image395.jpg",
    "label": ""
  },
  {
    "src": "image524.jpg",
    "label": ""
  },
  {
    "src": "image663.jpg",
    "label": ""
  },
  {
    "src": "image672.jpg",
    "label": ""
  },
  {
    "src": "image779.jpg",
    "label": ""
  },
  {
    "src": "image861.jpg",
    "label": ""
  },
  {
    "src": "image876.jpg",
    "label": ""
  },
  {
    "src": "image1051.jpg",
    "label": ""
  },
  {
    "src": "image1098.jpg",
    "label": ""
  }
]